{"description":"muestra mensaje error password obligatorio|work-space project login","passed":true,"pending":false,"os":"Windows","instanceId":14296,"browser":{"name":"chrome","version":"89.0.4389.82"},"message":"Passed.","trace":"","browserLogs":[{"level":"WARNING","message":"http://localhost:4200/polyfills.js 2557:8 \"[WDS] Warnings while compiling.\"","timestamp":1616009673190,"type":""},{"level":"WARNING","message":"http://localhost:4200/polyfills.js 2566:10 \"Emitted no files.\\r\\n\"","timestamp":1616009673191,"type":""}],"screenShotFile":"001f0004-00eb-003b-0014-00bd00ec00a0.png","timestamp":1616009672328,"duration":932}
