{"description":"debería mostrar mensaje error email no valido|work-space project login","passed":true,"pending":false,"os":"Windows","instanceId":21412,"browser":{"name":"chrome","version":"89.0.4389.82"},"message":"Passed.","trace":"","browserLogs":[{"level":"WARNING","message":"http://localhost:4200/polyfills.js 2557:8 \"[WDS] Warnings while compiling.\"","timestamp":1616009995604,"type":""},{"level":"WARNING","message":"http://localhost:4200/polyfills.js 2566:10 \"Emitted no files.\\r\\n\"","timestamp":1616009995604,"type":""}],"screenShotFile":"00300060-00e2-00ab-005a-000500c000c4.png","timestamp":1616009994764,"duration":985}
