{"description":"Muestra mensaje error ISBN obligatorio|workspace-project Prestamo","passed":true,"pending":false,"os":"Windows","instanceId":10436,"browser":{"name":"chrome","version":"89.0.4389.82"},"message":"Passed.","trace":"","browserLogs":[{"level":"WARNING","message":"http://localhost:4200/polyfills.js 2557:8 \"[WDS] Warnings while compiling.\"","timestamp":1616014396361,"type":""},{"level":"WARNING","message":"http://localhost:4200/polyfills.js 2566:10 \"Emitted no files.\\r\\n\"","timestamp":1616014396362,"type":""}],"screenShotFile":"00f70034-0081-00c2-00ae-000b004100cb.png","timestamp":1616014395508,"duration":925}
